clashroyalebuildabot/__init__.py
clashroyalebuildabot/screen.py
clashroyalebuildabot/bot/__init__.py
clashroyalebuildabot/bot/action.py
clashroyalebuildabot/bot/bot.py
clashroyalebuildabot/bot/pete/__init__.py
clashroyalebuildabot/bot/pete/pete_action.py
clashroyalebuildabot/bot/pete/pete_bot.py
clashroyalebuildabot/bot/random/__init__.py
clashroyalebuildabot/bot/random/random_bot.py
clashroyalebuildabot/bot/standard/__init__.py
clashroyalebuildabot/bot/standard/standard_action.py
clashroyalebuildabot/bot/standard/standard_bot.py
clashroyalebuildabot/bot/two_six_hog_cycle/__init__.py
clashroyalebuildabot/bot/two_six_hog_cycle/two_six_hog_cycle_action.py
clashroyalebuildabot/bot/two_six_hog_cycle/two_six_hog_cycle_bot.py
clashroyalebuildabot/data/__init__.py
clashroyalebuildabot/data/cards.csv
clashroyalebuildabot/data/constants.py
clashroyalebuildabot/data/number.onnx
clashroyalebuildabot/data/side.onnx
clashroyalebuildabot/data/unit.onnx
clashroyalebuildabot/data/images/cards/archer_queen.png
clashroyalebuildabot/data/images/cards/archers.png
clashroyalebuildabot/data/images/cards/arrows.png
clashroyalebuildabot/data/images/cards/balloon.png
clashroyalebuildabot/data/images/cards/bandit.png
clashroyalebuildabot/data/images/cards/barbarian_barrel.png
clashroyalebuildabot/data/images/cards/barbarian_hut.png
clashroyalebuildabot/data/images/cards/barbarians.png
clashroyalebuildabot/data/images/cards/bats.png
clashroyalebuildabot/data/images/cards/battle_healer.png
clashroyalebuildabot/data/images/cards/battle_ram.png
clashroyalebuildabot/data/images/cards/blank.png
clashroyalebuildabot/data/images/cards/bomb_tower.png
clashroyalebuildabot/data/images/cards/bomber.png
clashroyalebuildabot/data/images/cards/bowler.png
clashroyalebuildabot/data/images/cards/cannon.png
clashroyalebuildabot/data/images/cards/cannon_cart.png
clashroyalebuildabot/data/images/cards/clone.png
clashroyalebuildabot/data/images/cards/dark_prince.png
ClashRoyaleBuildABot-1.2.0.dist-info/LICENSE.md
ClashRoyaleBuildABot-1.2.0.dist-info/METADATA
ClashRoyaleBuildABot-1.2.0.dist-info/WHEEL
ClashRoyaleBuildABot-1.2.0.dist-info/top_level.txt
ClashRoyaleBuildABot-1.2.0.dist-info/RECORD
