Metadata-Version: 2.1
Name: ClashRoyaleBuildABot
Version: 1.2.0
Summary: A platform for creating bots to play Clash Royale
Home-page: https://github.com/Pbatch/ClashRoyaleBuildABot
Download-URL: https://github.com/Pbatch/ClashRoyaleBuildABot/releases
Author: pbatch
Keywords: machine-learning ai computer-vision adb clashroyale bluestacks yolov5
Classifier: Programming Language :: Python :: 3 :: Only
Classifier: Programming Language :: Python :: 3.6
Classifier: Programming Language :: Python :: 3.7
Classifier: Programming Language :: Python :: 3.8
Classifier: Programming Language :: Python :: 3.9
Requires-Python: >=3.6
License-File: LICENSE.md
Requires-Dist: Pillow
Requires-Dist: numpy
Requires-Dist: scipy
Requires-Dist: onnxruntime
